Workbook

Sheet Margin Calculator
A1: CATALYST IQ LABS | AMS MARGIN CALCULATOR
A2: Edit the YELLOW cells only. Everything else calculates automatically. Weekly hours pick the billing rate from the tier table on the right.
A4: INPUTS | E4: RATE TIERS
A5: Weekly contracted hours | B5: 20 | C5: Hours per week the client's subscription covers. Must fall inside the tier table (5–40). | E5: Tier | F5: Min hrs | G5: Max hrs | H5: Client $/hr
A6: 1099 consultant cost ($/hr) | B6: 105 | C6: What you pay the contractor per hour worked. | E6: Lite Engagement | F6: 5 | G6: 20 | H6: 189
A7: Overhead allocation ($/hr) | B7: 0 | C7: Your share of tools, insurance, admin, etc. per hour delivered. Leave $0 to ignore. | E7: Part-Time | F7: 21 | G7: 29 | H7: 180
A8: Target contribution margin | B8: 0.3 | C8: The minimum margin you want to keep after consultant cost and overhead. | E8: Full-Time | F8: 30 | G8: 40 | H8: 174
A9: Hours actually delivered (% of contracted) | B9: 1 | C9: 100% = consultant works exactly the contracted hours. Set 110% to test a client who runs 10% over. | E9: A tier starts at its Min hrs and runs until the next tier's Min. Keep tiers in order, smallest first.
A10: Billable weeks per year | B10: 52 | C10: 52 = bill every week. Use ~48 if the subscription pauses for holidays.
A11: Round subscription quote up to nearest | B11: 50 | C11: Rounds the client-facing monthly price to a clean number. Set $0 for no rounding.
A13: PRICING (AUTOMATIC)
A14: Tier selected | B14: =IF(AND($B$5>=$F$6,$B$5<=$G$8),INDEX($E$6:$E$8,MATCH($B$5,$F$6:$F$8,1)),"Out of range") -> Lite Engagement
A15: Client billing rate ($/hr) | B15: =IF(AND($B$5>=$F$6,$B$5<=$G$8),INDEX($H$6:$H$8,MATCH($B$5,$F$6:$F$8,1)),0) -> 189
A16: Hours check | B16: =IF(AND($B$5>=$F$6,$B$5<=$G$8),"OK – hours fall inside a tier","Hours outside "&$F$6&"–"&$G$8&" – no rate applies") -> OK – hours fall inside a tier
A18: MONTHLY RESULTS
A19: Monthly client revenue | B19: =B15*B5*$B$10/12 -> 16380 | C19: Billing rate × contracted hours × weeks per month.
A20: Suggested monthly subscription quote | B20: =IF(B11>0,CEILING(B19,B11),B19) -> 16400 | C20: The flat monthly price to put in front of the client — no hours shown.
A21: Monthly hours delivered (internal only) | B21: =B5*B9*$B$10/12 -> 86.666667
A22: Monthly 1099 delivery expense | B22: =B6*B21 -> 9100
A23: Monthly overhead allocation | B23: =B7*B21 -> 0
A24: Direct gross profit | B24: =B19-B22 -> 7280
A25: Direct gross margin | B25: =IFERROR(B24/B19,0) -> 0.44444444
A26: Contribution after overhead | B26: =B24-B23 -> 7280
A27: Contribution margin | B27: =IFERROR(B26/B19,0) -> 0.44444444
A28: Target check | B28: =IF(B19=0,"No revenue",IF(B27>=B8,"Meets target","Below target")) -> Meets target
A30: ANNUALIZED
A31: Annual revenue | B31: =B19*12 -> 196560
A32: Annual contribution | B32: =B26*12 -> 87360
A34: PRICING GUARDRAILS
A35: Minimum billing rate to hit target ($/hr) | B35: =IFERROR((B6+B7)*B9/(1-B8),0) -> 150 | C35: Lowest rate you could charge at these hours and still hit your target margin.
A36: Price headroom above minimum ($/hr) | B36: =B15-B35 -> 39 | C36: How much you could discount before dropping below target. Red = already below.
A37: Max hours/week you can deliver and still hit target | B37: =IFERROR(B15*B5*(1-B8)/(B6+B7),0) -> 25.2 | C37: If the consultant works more than this, the client becomes less profitable than your target.
A38: Overrun buffer (hours/week) | B38: =B37-B5*B9 -> 5.2 | C38: Extra hours per week the client can use before you fall below target.

Sheet Tier Comparison
A1: TIER COMPARISON
A2: Edit the yellow hours in column A. Cost, overhead, % delivered and target all come from the Margin Calculator tab, so this table always matches it.
A4: Weekly hours | B4: Tier | C4: Sell rate ($/hr) | D4: Revenue ($/mo) | E4: 1099 cost ($/mo) | F4: Overhead ($/mo) | G4: Contribution ($/mo) | H4: Contribution margin | I4: ="Floor rate @ "&TEXT('Margin Calculator'!$B$8,"0%")&" ($/hr)" -> Floor rate @ 30% ($/hr) | J4: Meets target?
A5: 5 | B5: =IF(AND(A5>='Margin Calculator'!$F$6,A5<='Margin Calculator'!$G$8),INDEX('Margin Calculator'!$E$6:$E$8,MATCH(A5,'Margin Calculator'!$F$6:$F$8,1)),"Out of range") -> Lite Engagement | C5: =IF(AND(A5>='Margin Calculator'!$F$6,A5<='Margin Calculator'!$G$8),INDEX('Margin Calculator'!$H$6:$H$8,MATCH(A5,'Margin Calculator'!$F$6:$F$8,1)),0) -> 189 | D5: =A5*C5*'Margin Calculator'!$B$10/12 -> 4095 | E5: ='Margin Calculator'!$B$6*A5*'Margin Calculator'!$B$9*'Margin Calculator'!$B$10/12 -> 2275 | F5: ='Margin Calculator'!$B$7*A5*'Margin Calculator'!$B$9*'Margin Calculator'!$B$10/12 -> 0 | G5: =D5-E5-F5 -> 1820 | H5: =IFERROR(G5/D5,0) -> 0.44444444 | I5: =IFERROR(('Margin Calculator'!$B$6+'Margin Calculator'!$B$7)*'Margin Calculator'!$B$9/(1-'Margin Calculator'!$B$8),0) -> 150 | J5: =IF(D5=0,"–",IF(H5>='Margin Calculator'!$B$8,"Yes","No")) -> Yes
A6: 10 | B6: =IF(AND(A6>='Margin Calculator'!$F$6,A6<='Margin Calculator'!$G$8),INDEX('Margin Calculator'!$E$6:$E$8,MATCH(A6,'Margin Calculator'!$F$6:$F$8,1)),"Out of range") -> Lite Engagement | C6: =IF(AND(A6>='Margin Calculator'!$F$6,A6<='Margin Calculator'!$G$8),INDEX('Margin Calculator'!$H$6:$H$8,MATCH(A6,'Margin Calculator'!$F$6:$F$8,1)),0) -> 189 | D6: =A6*C6*'Margin Calculator'!$B$10/12 -> 8190 | E6: ='Margin Calculator'!$B$6*A6*'Margin Calculator'!$B$9*'Margin Calculator'!$B$10/12 -> 4550 | F6: ='Margin Calculator'!$B$7*A6*'Margin Calculator'!$B$9*'Margin Calculator'!$B$10/12 -> 0 | G6: =D6-E6-F6 -> 3640 | H6: =IFERROR(G6/D6,0) -> 0.44444444 | I6: =IFERROR(('Margin Calculator'!$B$6+'Margin Calculator'!$B$7)*'Margin Calculator'!$B$9/(1-'Margin Calculator'!$B$8),0) -> 150 | J6: =IF(D6=0,"–",IF(H6>='Margin Calculator'!$B$8,"Yes","No")) -> Yes
A7: 15 | B7: =IF(AND(A7>='Margin Calculator'!$F$6,A7<='Margin Calculator'!$G$8),INDEX('Margin Calculator'!$E$6:$E$8,MATCH(A7,'Margin Calculator'!$F$6:$F$8,1)),"Out of range") -> Lite Engagement | C7: =IF(AND(A7>='Margin Calculator'!$F$6,A7<='Margin Calculator'!$G$8),INDEX('Margin Calculator'!$H$6:$H$8,MATCH(A7,'Margin Calculator'!$F$6:$F$8,1)),0) -> 189 | D7: =A7*C7*'Margin Calculator'!$B$10/12 -> 12285 | E7: ='Margin Calculator'!$B$6*A7*'Margin Calculator'!$B$9*'Margin Calculator'!$B$10/12 -> 6825 | F7: ='Margin Calculator'!$B$7*A7*'Margin Calculator'!$B$9*'Margin Calculator'!$B$10/12 -> 0 | G7: =D7-E7-F7 -> 5460 | H7: =IFERROR(G7/D7,0) -> 0.44444444 | I7: =IFERROR(('Margin Calculator'!$B$6+'Margin Calculator'!$B$7)*'Margin Calculator'!$B$9/(1-'Margin Calculator'!$B$8),0) -> 150 | J7: =IF(D7=0,"–",IF(H7>='Margin Calculator'!$B$8,"Yes","No")) -> Yes
A8: 20 | B8: =IF(AND(A8>='Margin Calculator'!$F$6,A8<='Margin Calculator'!$G$8),INDEX('Margin Calculator'!$E$6:$E$8,MATCH(A8,'Margin Calculator'!$F$6:$F$8,1)),"Out of range") -> Lite Engagement | C8: =IF(AND(A8>='Margin Calculator'!$F$6,A8<='Margin Calculator'!$G$8),INDEX('Margin Calculator'!$H$6:$H$8,MATCH(A8,'Margin Calculator'!$F$6:$F$8,1)),0) -> 189 | D8: =A8*C8*'Margin Calculator'!$B$10/12 -> 16380 | E8: ='Margin Calculator'!$B$6*A8*'Margin Calculator'!$B$9*'Margin Calculator'!$B$10/12 -> 9100 | F8: ='Margin Calculator'!$B$7*A8*'Margin Calculator'!$B$9*'Margin Calculator'!$B$10/12 -> 0 | G8: =D8-E8-F8 -> 7280 | H8: =IFERROR(G8/D8,0) -> 0.44444444 | I8: =IFERROR(('Margin Calculator'!$B$6+'Margin Calculator'!$B$7)*'Margin Calculator'!$B$9/(1-'Margin Calculator'!$B$8),0) -> 150 | J8: =IF(D8=0,"–",IF(H8>='Margin Calculator'!$B$8,"Yes","No")) -> Yes
A9: 25 | B9: =IF(AND(A9>='Margin Calculator'!$F$6,A9<='Margin Calculator'!$G$8),INDEX('Margin Calculator'!$E$6:$E$8,MATCH(A9,'Margin Calculator'!$F$6:$F$8,1)),"Out of range") -> Part-Time | C9: =IF(AND(A9>='Margin Calculator'!$F$6,A9<='Margin Calculator'!$G$8),INDEX('Margin Calculator'!$H$6:$H$8,MATCH(A9,'Margin Calculator'!$F$6:$F$8,1)),0) -> 180 | D9: =A9*C9*'Margin Calculator'!$B$10/12 -> 19500 | E9: ='Margin Calculator'!$B$6*A9*'Margin Calculator'!$B$9*'Margin Calculator'!$B$10/12 -> 11375 | F9: ='Margin Calculator'!$B$7*A9*'Margin Calculator'!$B$9*'Margin Calculator'!$B$10/12 -> 0 | G9: =D9-E9-F9 -> 8125 | H9: =IFERROR(G9/D9,0) -> 0.41666667 | I9: =IFERROR(('Margin Calculator'!$B$6+'Margin Calculator'!$B$7)*'Margin Calculator'!$B$9/(1-'Margin Calculator'!$B$8),0) -> 150 | J9: =IF(D9=0,"–",IF(H9>='Margin Calculator'!$B$8,"Yes","No")) -> Yes
A10: 30 | B10: =IF(AND(A10>='Margin Calculator'!$F$6,A10<='Margin Calculator'!$G$8),INDEX('Margin Calculator'!$E$6:$E$8,MATCH(A10,'Margin Calculator'!$F$6:$F$8,1)),"Out of range") -> Full-Time | C10: =IF(AND(A10>='Margin Calculator'!$F$6,A10<='Margin Calculator'!$G$8),INDEX('Margin Calculator'!$H$6:$H$8,MATCH(A10,'Margin Calculator'!$F$6:$F$8,1)),0) -> 174 | D10: =A10*C10*'Margin Calculator'!$B$10/12 -> 22620 | E10: ='Margin Calculator'!$B$6*A10*'Margin Calculator'!$B$9*'Margin Calculator'!$B$10/12 -> 13650 | F10: ='Margin Calculator'!$B$7*A10*'Margin Calculator'!$B$9*'Margin Calculator'!$B$10/12 -> 0 | G10: =D10-E10-F10 -> 8970 | H10: =IFERROR(G10/D10,0) -> 0.39655172 | I10: =IFERROR(('Margin Calculator'!$B$6+'Margin Calculator'!$B$7)*'Margin Calculator'!$B$9/(1-'Margin Calculator'!$B$8),0) -> 150 | J10: =IF(D10=0,"–",IF(H10>='Margin Calculator'!$B$8,"Yes","No")) -> Yes
A11: 35 | B11: =IF(AND(A11>='Margin Calculator'!$F$6,A11<='Margin Calculator'!$G$8),INDEX('Margin Calculator'!$E$6:$E$8,MATCH(A11,'Margin Calculator'!$F$6:$F$8,1)),"Out of range") -> Full-Time | C11: =IF(AND(A11>='Margin Calculator'!$F$6,A11<='Margin Calculator'!$G$8),INDEX('Margin Calculator'!$H$6:$H$8,MATCH(A11,'Margin Calculator'!$F$6:$F$8,1)),0) -> 174 | D11: =A11*C11*'Margin Calculator'!$B$10/12 -> 26390 | E11: ='Margin Calculator'!$B$6*A11*'Margin Calculator'!$B$9*'Margin Calculator'!$B$10/12 -> 15925 | F11: ='Margin Calculator'!$B$7*A11*'Margin Calculator'!$B$9*'Margin Calculator'!$B$10/12 -> 0 | G11: =D11-E11-F11 -> 10465 | H11: =IFERROR(G11/D11,0) -> 0.39655172 | I11: =IFERROR(('Margin Calculator'!$B$6+'Margin Calculator'!$B$7)*'Margin Calculator'!$B$9/(1-'Margin Calculator'!$B$8),0) -> 150 | J11: =IF(D11=0,"–",IF(H11>='Margin Calculator'!$B$8,"Yes","No")) -> Yes
A12: 40 | B12: =IF(AND(A12>='Margin Calculator'!$F$6,A12<='Margin Calculator'!$G$8),INDEX('Margin Calculator'!$E$6:$E$8,MATCH(A12,'Margin Calculator'!$F$6:$F$8,1)),"Out of range") -> Full-Time | C12: =IF(AND(A12>='Margin Calculator'!$F$6,A12<='Margin Calculator'!$G$8),INDEX('Margin Calculator'!$H$6:$H$8,MATCH(A12,'Margin Calculator'!$F$6:$F$8,1)),0) -> 174 | D12: =A12*C12*'Margin Calculator'!$B$10/12 -> 30160 | E12: ='Margin Calculator'!$B$6*A12*'Margin Calculator'!$B$9*'Margin Calculator'!$B$10/12 -> 18200 | F12: ='Margin Calculator'!$B$7*A12*'Margin Calculator'!$B$9*'Margin Calculator'!$B$10/12 -> 0 | G12: =D12-E12-F12 -> 11960 | H12: =IFERROR(G12/D12,0) -> 0.39655172 | I12: =IFERROR(('Margin Calculator'!$B$6+'Margin Calculator'!$B$7)*'Margin Calculator'!$B$9/(1-'Margin Calculator'!$B$8),0) -> 150 | J12: =IF(D12=0,"–",IF(H12>='Margin Calculator'!$B$8,"Yes","No")) -> Yes

Sheet Client Portfolio
A1: CLIENT PORTFOLIO
A2: One row per client: type the client name and weekly hours (yellow). Leave the 1099 cost blank to use the default from the Margin Calculator, or enter a different rate for that client's consultant.
A4: Client | B4: Weekly hours | C4: 1099 cost ($/hr) (blank = default) | D4: Tier | E4: Rate ($/hr) | F4: Subscription ($/mo) | G4: 1099 cost ($/mo) | H4: Overhead ($/mo) | I4: Contribution ($/mo) | J4: Margin | K4: Meets target?
D5: =IF(B5<>"",IF(AND(B5>='Margin Calculator'!$F$6,B5<='Margin Calculator'!$G$8),INDEX('Margin Calculator'!$E$6:$E$8,MATCH(B5,'Margin Calculator'!$F$6:$F$8,1)),"Out of range"),"") | E5: =IF(B5<>"",IF(AND(B5>='Margin Calculator'!$F$6,B5<='Margin Calculator'!$G$8),INDEX('Margin Calculator'!$H$6:$H$8,MATCH(B5,'Margin Calculator'!$F$6:$F$8,1)),0),"") | F5: =IF(B5<>"",IF('Margin Calculator'!$B$11>0,CEILING(E5*B5*'Margin Calculator'!$B$10/12,'Margin Calculator'!$B$11),E5*B5*'Margin Calculator'!$B$10/12),"") | G5: =IF(B5<>"",IF(C5="",'Margin Calculator'!$B$6,C5)*B5*'Margin Calculator'!$B$9*'Margin Calculator'!$B$10/12,"") | H5: =IF(B5<>"",'Margin Calculator'!$B$7*B5*'Margin Calculator'!$B$9*'Margin Calculator'!$B$10/12,"") | I5: =IF(B5<>"",F5-G5-H5,"") | J5: =IF(B5<>"",IFERROR(I5/F5,0),"") | K5: =IF(B5<>"",IF(E5=0,"Fix hours",IF(J5>='Margin Calculator'!$B$8,"Yes","No")),"")
D6: =IF(B6<>"",IF(AND(B6>='Margin Calculator'!$F$6,B6<='Margin Calculator'!$G$8),INDEX('Margin Calculator'!$E$6:$E$8,MATCH(B6,'Margin Calculator'!$F$6:$F$8,1)),"Out of range"),"") | E6: =IF(B6<>"",IF(AND(B6>='Margin Calculator'!$F$6,B6<='Margin Calculator'!$G$8),INDEX('Margin Calculator'!$H$6:$H$8,MATCH(B6,'Margin Calculator'!$F$6:$F$8,1)),0),"") | F6: =IF(B6<>"",IF('Margin Calculator'!$B$11>0,CEILING(E6*B6*'Margin Calculator'!$B$10/12,'Margin Calculator'!$B$11),E6*B6*'Margin Calculator'!$B$10/12),"") | G6: =IF(B6<>"",IF(C6="",'Margin Calculator'!$B$6,C6)*B6*'Margin Calculator'!$B$9*'Margin Calculator'!$B$10/12,"") | H6: =IF(B6<>"",'Margin Calculator'!$B$7*B6*'Margin Calculator'!$B$9*'Margin Calculator'!$B$10/12,"") | I6: =IF(B6<>"",F6-G6-H6,"") | J6: =IF(B6<>"",IFERROR(I6/F6,0),"") | K6: =IF(B6<>"",IF(E6=0,"Fix hours",IF(J6>='Margin Calculator'!$B$8,"Yes","No")),"")
D7: =IF(B7<>"",IF(AND(B7>='Margin Calculator'!$F$6,B7<='Margin Calculator'!$G$8),INDEX('Margin Calculator'!$E$6:$E$8,MATCH(B7,'Margin Calculator'!$F$6:$F$8,1)),"Out of range"),"") | E7: =IF(B7<>"",IF(AND(B7>='Margin Calculator'!$F$6,B7<='Margin Calculator'!$G$8),INDEX('Margin Calculator'!$H$6:$H$8,MATCH(B7,'Margin Calculator'!$F$6:$F$8,1)),0),"") | F7: =IF(B7<>"",IF('Margin Calculator'!$B$11>0,CEILING(E7*B7*'Margin Calculator'!$B$10/12,'Margin Calculator'!$B$11),E7*B7*'Margin Calculator'!$B$10/12),"") | G7: =IF(B7<>"",IF(C7="",'Margin Calculator'!$B$6,C7)*B7*'Margin Calculator'!$B$9*'Margin Calculator'!$B$10/12,"") | H7: =IF(B7<>"",'Margin Calculator'!$B$7*B7*'Margin Calculator'!$B$9*'Margin Calculator'!$B$10/12,"") | I7: =IF(B7<>"",F7-G7-H7,"") | J7: =IF(B7<>"",IFERROR(I7/F7,0),"") | K7: =IF(B7<>"",IF(E7=0,"Fix hours",IF(J7>='Margin Calculator'!$B$8,"Yes","No")),"")
D8: =IF(B8<>"",IF(AND(B8>='Margin Calculator'!$F$6,B8<='Margin Calculator'!$G$8),INDEX('Margin Calculator'!$E$6:$E$8,MATCH(B8,'Margin Calculator'!$F$6:$F$8,1)),"Out of range"),"") | E8: =IF(B8<>"",IF(AND(B8>='Margin Calculator'!$F$6,B8<='Margin Calculator'!$G$8),INDEX('Margin Calculator'!$H$6:$H$8,MATCH(B8,'Margin Calculator'!$F$6:$F$8,1)),0),"") | F8: =IF(B8<>"",IF('Margin Calculator'!$B$11>0,CEILING(E8*B8*'Margin Calculator'!$B$10/12,'Margin Calculator'!$B$11),E8*B8*'Margin Calculator'!$B$10/12),"") | G8: =IF(B8<>"",IF(C8="",'Margin Calculator'!$B$6,C8)*B8*'Margin Calculator'!$B$9*'Margin Calculator'!$B$10/12,"") | H8: =IF(B8<>"",'Margin Calculator'!$B$7*B8*'Margin Calculator'!$B$9*'Margin Calculator'!$B$10/12,"") | I8: =IF(B8<>"",F8-G8-H8,"") | J8: =IF(B8<>"",IFERROR(I8/F8,0),"") | K8: =IF(B8<>"",IF(E8=0,"Fix hours",IF(J8>='Margin Calculator'!$B$8,"Yes","No")),"")
D9: =IF(B9<>"",IF(AND(B9>='Margin Calculator'!$F$6,B9<='Margin Calculator'!$G$8),INDEX('Margin Calculator'!$E$6:$E$8,MATCH(B9,'Margin Calculator'!$F$6:$F$8,1)),"Out of range"),"") | E9: =IF(B9<>"",IF(AND(B9>='Margin Calculator'!$F$6,B9<='Margin Calculator'!$G$8),INDEX('Margin Calculator'!$H$6:$H$8,MATCH(B9,'Margin Calculator'!$F$6:$F$8,1)),0),"") | F9: =IF(B9<>"",IF('Margin Calculator'!$B$11>0,CEILING(E9*B9*'Margin Calculator'!$B$10/12,'Margin Calculator'!$B$11),E9*B9*'Margin Calculator'!$B$10/12),"") | G9: =IF(B9<>"",IF(C9="",'Margin Calculator'!$B$6,C9)*B9*'Margin Calculator'!$B$9*'Margin Calculator'!$B$10/12,"") | H9: =IF(B9<>"",'Margin Calculator'!$B$7*B9*'Margin Calculator'!$B$9*'Margin Calculator'!$B$10/12,"") | I9: =IF(B9<>"",F9-G9-H9,"") | J9: =IF(B9<>"",IFERROR(I9/F9,0),"") | K9: =IF(B9<>"",IF(E9=0,"Fix hours",IF(J9>='Margin Calculator'!$B$8,"Yes","No")),"")
D10: =IF(B10<>"",IF(AND(B10>='Margin Calculator'!$F$6,B10<='Margin Calculator'!$G$8),INDEX('Margin Calculator'!$E$6:$E$8,MATCH(B10,'Margin Calculator'!$F$6:$F$8,1)),"Out of range"),"") | E10: =IF(B10<>"",IF(AND(B10>='Margin Calculator'!$F$6,B10<='Margin Calculator'!$G$8),INDEX('Margin Calculator'!$H$6:$H$8,MATCH(B10,'Margin Calculator'!$F$6:$F$8,1)),0),"") | F10: =IF(B10<>"",IF('Margin Calculator'!$B$11>0,CEILING(E10*B10*'Margin Calculator'!$B$10/12,'Margin Calculator'!$B$11),E10*B10*'Margin Calculator'!$B$10/12),"") | G10: =IF(B10<>"",IF(C10="",'Margin Calculator'!$B$6,C10)*B10*'Margin Calculator'!$B$9*'Margin Calculator'!$B$10/12,"") | H10: =IF(B10<>"",'Margin Calculator'!$B$7*B10*'Margin Calculator'!$B$9*'Margin Calculator'!$B$10/12,"") | I10: =IF(B10<>"",F10-G10-H10,"") | J10: =IF(B10<>"",IFERROR(I10/F10,0),"") | K10: =IF(B10<>"",IF(E10=0,"Fix hours",IF(J10>='Margin Calculator'!$B$8,"Yes","No")),"")
D11: =IF(B11<>"",IF(AND(B11>='Margin Calculator'!$F$6,B11<='Margin Calculator'!$G$8),INDEX('Margin Calculator'!$E$6:$E$8,MATCH(B11,'Margin Calculator'!$F$6:$F$8,1)),"Out of range"),"") | E11: =IF(B11<>"",IF(AND(B11>='Margin Calculator'!$F$6,B11<='Margin Calculator'!$G$8),INDEX('Margin Calculator'!$H$6:$H$8,MATCH(B11,'Margin Calculator'!$F$6:$F$8,1)),0),"") | F11: =IF(B11<>"",IF('Margin Calculator'!$B$11>0,CEILING(E11*B11*'Margin Calculator'!$B$10/12,'Margin Calculator'!$B$11),E11*B11*'Margin Calculator'!$B$10/12),"") | G11: =IF(B11<>"",IF(C11="",'Margin Calculator'!$B$6,C11)*B11*'Margin Calculator'!$B$9*'Margin Calculator'!$B$10/12,"") | H11: =IF(B11<>"",'Margin Calculator'!$B$7*B11*'Margin Calculator'!$B$9*'Margin Calculator'!$B$10/12,"") | I11: =IF(B11<>"",F11-G11-H11,"") | J11: =IF(B11<>"",IFERROR(I11/F11,0),"") | K11: =IF(B11<>"",IF(E11=0,"Fix hours",IF(J11>='Margin Calculator'!$B$8,"Yes","No")),"")
D12: =IF(B12<>"",IF(AND(B12>='Margin Calculator'!$F$6,B12<='Margin Calculator'!$G$8),INDEX('Margin Calculator'!$E$6:$E$8,MATCH(B12,'Margin Calculator'!$F$6:$F$8,1)),"Out of range"),"") | E12: =IF(B12<>"",IF(AND(B12>='Margin Calculator'!$F$6,B12<='Margin Calculator'!$G$8),INDEX('Margin Calculator'!$H$6:$H$8,MATCH(B12,'Margin Calculator'!$F$6:$F$8,1)),0),"") | F12: =IF(B12<>"",IF('Margin Calculator'!$B$11>0,CEILING(E12*B12*'Margin Calculator'!$B$10/12,'Margin Calculator'!$B$11),E12*B12*'Margin Calculator'!$B$10/12),"") | G12: =IF(B12<>"",IF(C12="",'Margin Calculator'!$B$6,C12)*B12*'Margin Calculator'!$B$9*'Margin Calculator'!$B$10/12,"") | H12: =IF(B12<>"",'Margin Calculator'!$B$7*B12*'Margin Calculator'!$B$9*'Margin Calculator'!$B$10/12,"") | I12: =IF(B12<>"",F12-G12-H12,"") | J12: =IF(B12<>"",IFERROR(I12/F12,0),"") | K12: =IF(B12<>"",IF(E12=0,"Fix hours",IF(J12>='Margin Calculator'!$B$8,"Yes","No")),"")
D13: =IF(B13<>"",IF(AND(B13>='Margin Calculator'!$F$6,B13<='Margin Calculator'!$G$8),INDEX('Margin Calculator'!$E$6:$E$8,MATCH(B13,'Margin Calculator'!$F$6:$F$8,1)),"Out of range"),"") | E13: =IF(B13<>"",IF(AND(B13>='Margin Calculator'!$F$6,B13<='Margin Calculator'!$G$8),INDEX('Margin Calculator'!$H$6:$H$8,MATCH(B13,'Margin Calculator'!$F$6:$F$8,1)),0),"") | F13: =IF(B13<>"",IF('Margin Calculator'!$B$11>0,CEILING(E13*B13*'Margin Calculator'!$B$10/12,'Margin Calculator'!$B$11),E13*B13*'Margin Calculator'!$B$10/12),"") | G13: =IF(B13<>"",IF(C13="",'Margin Calculator'!$B$6,C13)*B13*'Margin Calculator'!$B$9*'Margin Calculator'!$B$10/12,"") | H13: =IF(B13<>"",'Margin Calculator'!$B$7*B13*'Margin Calculator'!$B$9*'Margin Calculator'!$B$10/12,"") | I13: =IF(B13<>"",F13-G13-H13,"") | J13: =IF(B13<>"",IFERROR(I13/F13,0),"") | K13: =IF(B13<>"",IF(E13=0,"Fix hours",IF(J13>='Margin Calculator'!$B$8,"Yes","No")),"")
D14: =IF(B14<>"",IF(AND(B14>='Margin Calculator'!$F$6,B14<='Margin Calculator'!$G$8),INDEX('Margin Calculator'!$E$6:$E$8,MATCH(B14,'Margin Calculator'!$F$6:$F$8,1)),"Out of range"),"") | E14: =IF(B14<>"",IF(AND(B14>='Margin Calculator'!$F$6,B14<='Margin Calculator'!$G$8),INDEX('Margin Calculator'!$H$6:$H$8,MATCH(B14,'Margin Calculator'!$F$6:$F$8,1)),0),"") | F14: =IF(B14<>"",IF('Margin Calculator'!$B$11>0,CEILING(E14*B14*'Margin Calculator'!$B$10/12,'Margin Calculator'!$B$11),E14*B14*'Margin Calculator'!$B$10/12),"") | G14: =IF(B14<>"",IF(C14="",'Margin Calculator'!$B$6,C14)*B14*'Margin Calculator'!$B$9*'Margin Calculator'!$B$10/12,"") | H14: =IF(B14<>"",'Margin Calculator'!$B$7*B14*'Margin Calculator'!$B$9*'Margin Calculator'!$B$10/12,"") | I14: =IF(B14<>"",F14-G14-H14,"") | J14: =IF(B14<>"",IFERROR(I14/F14,0),"") | K14: =IF(B14<>"",IF(E14=0,"Fix hours",IF(J14>='Margin Calculator'!$B$8,"Yes","No")),"")
D15: =IF(B15<>"",IF(AND(B15>='Margin Calculator'!$F$6,B15<='Margin Calculator'!$G$8),INDEX('Margin Calculator'!$E$6:$E$8,MATCH(B15,'Margin Calculator'!$F$6:$F$8,1)),"Out of range"),"") | E15: =IF(B15<>"",IF(AND(B15>='Margin Calculator'!$F$6,B15<='Margin Calculator'!$G$8),INDEX('Margin Calculator'!$H$6:$H$8,MATCH(B15,'Margin Calculator'!$F$6:$F$8,1)),0),"") | F15: =IF(B15<>"",IF('Margin Calculator'!$B$11>0,CEILING(E15*B15*'Margin Calculator'!$B$10/12,'Margin Calculator'!$B$11),E15*B15*'Margin Calculator'!$B$10/12),"") | G15: =IF(B15<>"",IF(C15="",'Margin Calculator'!$B$6,C15)*B15*'Margin Calculator'!$B$9*'Margin Calculator'!$B$10/12,"") | H15: =IF(B15<>"",'Margin Calculator'!$B$7*B15*'Margin Calculator'!$B$9*'Margin Calculator'!$B$10/12,"") | I15: =IF(B15<>"",F15-G15-H15,"") | J15: =IF(B15<>"",IFERROR(I15/F15,0),"") | K15: =IF(B15<>"",IF(E15=0,"Fix hours",IF(J15>='Margin Calculator'!$B$8,"Yes","No")),"")
D16: =IF(B16<>"",IF(AND(B16>='Margin Calculator'!$F$6,B16<='Margin Calculator'!$G$8),INDEX('Margin Calculator'!$E$6:$E$8,MATCH(B16,'Margin Calculator'!$F$6:$F$8,1)),"Out of range"),"") | E16: =IF(B16<>"",IF(AND(B16>='Margin Calculator'!$F$6,B16<='Margin Calculator'!$G$8),INDEX('Margin Calculator'!$H$6:$H$8,MATCH(B16,'Margin Calculator'!$F$6:$F$8,1)),0),"") | F16: =IF(B16<>"",IF('Margin Calculator'!$B$11>0,CEILING(E16*B16*'Margin Calculator'!$B$10/12,'Margin Calculator'!$B$11),E16*B16*'Margin Calculator'!$B$10/12),"") | G16: =IF(B16<>"",IF(C16="",'Margin Calculator'!$B$6,C16)*B16*'Margin Calculator'!$B$9*'Margin Calculator'!$B$10/12,"") | H16: =IF(B16<>"",'Margin Calculator'!$B$7*B16*'Margin Calculator'!$B$9*'Margin Calculator'!$B$10/12,"") | I16: =IF(B16<>"",F16-G16-H16,"") | J16: =IF(B16<>"",IFERROR(I16/F16,0),"") | K16: =IF(B16<>"",IF(E16=0,"Fix hours",IF(J16>='Margin Calculator'!$B$8,"Yes","No")),"")
... D24: =IF(B24<>"",IF(AND(B24>='Margin Calculator'!$F$6,B24<='Margin Calculator'!$G$8),INDEX('Margin Calculator'!$E$6:$E$8,MATCH(B24,'Margin Calculator'!$F$6:$F$8,1)),"Out of range"),"") | E24: =IF(B24<>"",IF(AND(B24>='Margin Calculator'!$F$6,B24<='Margin Calculator'!$G$8),INDEX('Margin Calculator'!$H$6:$H$8,MATCH(B24,'Margin Calculator'!$F$6:$F$8,1)),0),"") | F24: =IF(B24<>"",IF('Margin Calculator'!$B$11>0,CEILING(E24*B24*'Margin Calculator'!$B$10/12,'Margin Calculator'!$B$11),E24*B24*'Margin Calculator'!$B$10/12),"") | G24: =IF(B24<>"",IF(C24="",'Margin Calculator'!$B$6,C24)*B24*'Margin Calculator'!$B$9*'Margin Calculator'!$B$10/12,"") | H24: =IF(B24<>"",'Margin Calculator'!$B$7*B24*'Margin Calculator'!$B$9*'Margin Calculator'!$B$10/12,"") | I24: =IF(B24<>"",F24-G24-H24,"") | J24: =IF(B24<>"",IFERROR(I24/F24,0),"") | K24: =IF(B24<>"",IF(E24=0,"Fix hours",IF(J24>='Margin Calculator'!$B$8,"Yes","No")),"")
A26: PORTFOLIO TOTAL | B26: =SUM(B5:B24) -> 0 | F26: =SUM(F5:F24) -> 0 | G26: =SUM(G5:G24) -> 0 | H26: =SUM(H5:H24) -> 0 | I26: =SUM(I5:I24) -> 0 | J26: =IFERROR(I26/F26,0) -> 0
A28: Active clients | D28: =COUNTA(A5:A24) -> 0
A29: Annual recurring revenue | D29: =F26*12 -> 0
A30: Annual contribution | D30: =I26*12 -> 0
A31: Consultant capacity needed (FTEs @ 40 hrs/wk) | D31: =B26*'Margin Calculator'!$B$9/40 -> 0
